[{"collectionName":"Tanjavur","primaryKey":"788c4ec8-79c7-4857-bd0f-5fde89576d53","requests":[{"name":"","request":"{\"input\":{\"bounds\":{\"bbox\":[79,10.57,79.047,10.617]},\"data\":[{\"dataFilter\":{\"timeRange\":{\"from\":\"2023-01-01T00:00:00Z\",\"to\":\"2025-09-05T23:59:59Z\"},\"maxCloudCoverage\":10},\"type\":\"sentinel-2-l2a\"}]},\"output\":{\"width\":2023.313,\"height\":2058.238,\"responses\":[{\"identifier\":\"default\",\"format\":{\"type\":\"image/tiff\"}}]},\"evalscript\":\"//VERSION=3\\n\\nfunction setup() {\\n  return {\\n    input: [\\\"B02\\\", \\\"B03\\\", \\\"B04\\\"],\\n    output: { bands: 3 }\\n  };\\n}\\n\\nfunction evaluatePixel(sample) {\\n  return [2.5 * sample.B04, 2.5 * sample.B03, 2.5 * sample.B02];\\n}\"}","mode":"PROCESS"}]}]